grect/__init__.py
grect-0.0.1.dist-info/LICENSE
grect-0.0.1.dist-info/METADATA
grect-0.0.1.dist-info/WHEEL
grect-0.0.1.dist-info/top_level.txt
grect-0.0.1.dist-info/RECORD
